gml/__init__.py
gml/compile.py
giml-0.0.1.dist-info/METADATA
giml-0.0.1.dist-info/WHEEL
giml-0.0.1.dist-info/top_level.txt
giml-0.0.1.dist-info/RECORD
